{
  "skills": [
    "Python",
    "Java",
    "JavaScript",
    "TypeScript",
    "C++",
    "C#",
    "Go",
    "Rust",
    "Ruby",
    "PHP",
    "Swift",
    "Kotlin",
    "Scala",
    "R",
    "MATLAB",
    "React",
    "Angular",
    "Vue",
    "Next.js",
    "Nuxt.js",
    "Svelte",
    "Node.js",
    "Express",
    "FastAPI",
    "Django",
    "Flask",
    "Spring Boot",
    "Laravel",
    "Ruby on Rails",
    "ASP.NET",
    "PostgreSQL",
    "MySQL",
    "MongoDB",
    "Redis",
    "Elasticsearch",
    "SQLite",
    "Oracle",
    "Cassandra",
    "DynamoDB",
    "Docker",
    "Kubernetes",
    "AWS",
    "Azure",
    "GCP",
    "Terraform",
    "Jenkins",
    "GitHub Actions",
    "CircleCI",
    "Ansible",
    "Machine Learning",
    "Deep Learning",
    "NLP",
    "Computer Vision",
    "TensorFlow",
    "PyTorch",
    "scikit-learn",
    "Keras",
    "Pandas",
    "NumPy",
    "Git",
    "Linux",
    "Bash",
    "REST API",
    "GraphQL",
    "gRPC",
    "HTML",
    "CSS",
    "Tailwind",
    "Bootstrap",
    "SASS",
    "Agile",
    "Scrum",
    "Jira",
    "Figma",
    "Postman",
    "Data Structures",
    "Algorithms",
    "System Design",
    "OOP",
    "Microservices",
    "CI/CD",
    "DevOps",
    "Cloud Computing",
    "Communication",
    "Teamwork",
    "Problem Solving",
    "Leadership",
    "SQL",
    "Excel",
    "MS Excel",
    "Power BI",
    "Tableau",
    "Financial Modeling",
    "Financial Analysis",
    "Accounting",
    "Budgeting",
    "Forecasting",
    "SAP",
    "Tally",
    "QuickBooks",
    "Risk Management",
    "Bloomberg",
    "Financial Reporting",
    "SEO",
    "SEM",
    "Google Analytics",
    "Social Media Marketing",
    "Content Marketing",
    "Email Marketing",
    "Google Ads",
    "Copywriting",
    "Brand Management",
    "Market Research",
    "HubSpot",
    "Digital Marketing",
    "Salesforce",
    "CRM",
    "Recruitment",
    "Talent Acquisition",
    "Payroll",
    "Employee Relations",
    "Performance Management",
    "Workday",
    "HR Management",
    "Training and Development",
    "AutoCAD",
    "SolidWorks",
    "Thermodynamics",
    "Manufacturing",
    "Structural Analysis",
    "ANSYS",
    "Project Management",
    "Business Analysis",
    "Data Analysis",
    "Statistics",
    "Research",
    "Presentation",
    "Negotiation",
    "Strategic Planning",
    "Supply Chain",
    "Logistics",
    "Operations Management"
  ],
  "categories": {
    "language": [
      "Python",
      "Java",
      "JavaScript",
      "TypeScript",
      "C++",
      "C#",
      "Go",
      "Rust",
      "Ruby",
      "PHP",
      "Swift",
      "Kotlin",
      "Scala",
      "R"
    ],
    "framework": [
      "React",
      "Angular",
      "Vue",
      "Next.js",
      "Node.js",
      "Express",
      "FastAPI",
      "Django",
      "Flask",
      "Spring Boot",
      "Laravel"
    ],
    "tool": [
      "Docker",
      "Kubernetes",
      "Git",
      "Jenkins",
      "Terraform",
      "GitHub Actions",
      "Jira",
      "Figma",
      "Postman",
      "Linux"
    ],
    "database": [
      "PostgreSQL",
      "MySQL",
      "MongoDB",
      "Redis",
      "Elasticsearch",
      "SQLite",
      "Oracle",
      "Cassandra",
      "DynamoDB"
    ],
    "cloud": [
      "AWS",
      "Azure",
      "GCP",
      "Cloud Computing"
    ],
    "ml": [
      "Machine Learning",
      "Deep Learning",
      "NLP",
      "Computer Vision",
      "TensorFlow",
      "PyTorch",
      "scikit-learn",
      "Keras"
    ],
    "soft": [
      "Communication",
      "Teamwork",
      "Problem Solving",
      "Leadership",
      "Agile",
      "Scrum",
      "Project Management",
      "Presentation",
      "Negotiation",
      "Strategic Planning",
      "Research"
    ],
    "finance": [
      "Excel",
      "MS Excel",
      "SQL",
      "Power BI",
      "Tableau",
      "Financial Modeling",
      "Financial Analysis",
      "Accounting",
      "Budgeting",
      "Forecasting",
      "SAP",
      "Tally",
      "QuickBooks",
      "Risk Management",
      "Bloomberg",
      "Financial Reporting",
      "Statistics",
      "Data Analysis"
    ],
    "marketing": [
      "SEO",
      "SEM",
      "Google Analytics",
      "Social Media Marketing",
      "Content Marketing",
      "Email Marketing",
      "Google Ads",
      "Copywriting",
      "Brand Management",
      "Market Research",
      "HubSpot",
      "Digital Marketing",
      "Salesforce",
      "CRM"
    ],
    "hr": [
      "Recruitment",
      "Talent Acquisition",
      "Payroll",
      "Employee Relations",
      "Performance Management",
      "Workday",
      "HR Management",
      "Training and Development"
    ],
    "engineering": [
      "AutoCAD",
      "SolidWorks",
      "MATLAB",
      "Thermodynamics",
      "Manufacturing",
      "Structural Analysis",
      "ANSYS"
    ],
    "operations": [
      "Supply Chain",
      "Logistics",
      "Operations Management",
      "Business Analysis"
    ]
  }
}
